p99_bluesky/__init__.py
p99_bluesky/__main__.py
p99_bluesky/_version.py
p99_bluesky/log.py
p99_bluesky/beamlines/p99.py
p99_bluesky/devices/__init__.py
p99_bluesky/devices/stages.py
p99_bluesky/devices/epics/__init__.py
p99_bluesky/devices/p99/__init__.py
p99_bluesky/devices/p99/sample_stage.py
p99_bluesky/plan_stubs/__init__.py
p99_bluesky/plan_stubs/detector_plans.py
p99_bluesky/plan_stubs/motor_plan.py
p99_bluesky/plans/__init__.py
p99_bluesky/plans/ad_plans.py
p99_bluesky/plans/fast_scan.py
p99_bluesky/plans/stxm.py
p99_bluesky/sim/__init__.py
p99_bluesky/sim/sim_stages.py
p99_bluesky/utility/__init__.py
p99_bluesky/utility/utility.py
p99_bluesky-0.1.1.1.dist-info/licenses/LICENSE
p99_bluesky-0.1.1.1.dist-info/METADATA
p99_bluesky-0.1.1.1.dist-info/WHEEL
p99_bluesky-0.1.1.1.dist-info/entry_points.txt
p99_bluesky-0.1.1.1.dist-info/top_level.txt
p99_bluesky-0.1.1.1.dist-info/RECORD
