Metadata-Version: 2.4
Name: p99-bluesky
Version: 0.1.1.1
Summary: p99 sandbox
Author-email: Raymond Fan <raymond.fan@diamond.ac.uk>
License:                                  Apache License
Project-URL: GitHub, https://github.com/DiamondLightSource/p99-bluesky
Classifier: Development Status :: 3 - Alpha
Classifier: License :: OSI Approved :: Apache Software License
Classifier: Programming Language :: Python :: 3.10
Classifier: Programming Language :: Python :: 3.11
Classifier: Programming Language :: Python :: 3.12
Requires-Python: >=3.10
License-File: LICENSE
Requires-Dist: blueapi
Requires-Dist: ophyd
Requires-Dist: dls-dodal
Requires-Dist: ophyd-async
Requires-Dist: bluesky
Requires-Dist: jupyter
Requires-Dist: ipython
Requires-Dist: matplotlib
Requires-Dist: numpy
Requires-Dist: pyepics
Provides-Extra: dev
Requires-Dist: copier; extra == "dev"
Requires-Dist: myst-parser; extra == "dev"
Requires-Dist: pipdeptree; extra == "dev"
Requires-Dist: pre-commit; extra == "dev"
Requires-Dist: pydata-sphinx-theme>=0.12; extra == "dev"
Requires-Dist: pyright; extra == "dev"
Requires-Dist: pytest; extra == "dev"
Requires-Dist: pytest-cov; extra == "dev"
Requires-Dist: ruff; extra == "dev"
Requires-Dist: sphinx-autobuild; extra == "dev"
Requires-Dist: sphinx-copybutton; extra == "dev"
Requires-Dist: sphinx-design; extra == "dev"
Requires-Dist: autodoc-pydantic; extra == "dev"
Requires-Dist: sphinxcontrib-mermaid; extra == "dev"
Requires-Dist: sphinxcontrib-openapi; extra == "dev"
Requires-Dist: sphinx-click; extra == "dev"
Requires-Dist: tox-direct; extra == "dev"
Requires-Dist: types-mock; extra == "dev"
Requires-Dist: pytest-asyncio; extra == "dev"
Requires-Dist: super_state_machine; extra == "dev"
Requires-Dist: h5py; extra == "dev"
Requires-Dist: ipython; extra == "dev"
Requires-Dist: ipywidgets; extra == "dev"
Requires-Dist: numpydoc; extra == "dev"
Requires-Dist: pickleshare; extra == "dev"
Requires-Dist: pyside6; extra == "dev"
Requires-Dist: pytest-faulthandler; extra == "dev"
Requires-Dist: pytest-rerunfailures; extra == "dev"
Requires-Dist: pytest-timeout; extra == "dev"
Requires-Dist: types-pyyaml; extra == "dev"
Requires-Dist: softioc; extra == "dev"
Requires-Dist: cothread; extra == "dev"
Dynamic: license-file
